beetsplug/folkways/__init__.py
beetsplug/folkways/definitions.py
beetsplug/folkways/extract_info.py
beetsplug/folkways/http.py
beetsplug/folkways/record.py
beetsplug/folkways/search.py
beetsplug/folkways/track.py
beets_folkways-0.1.2.dist-info/METADATA
beets_folkways-0.1.2.dist-info/WHEEL
beets_folkways-0.1.2.dist-info/top_level.txt
beets_folkways-0.1.2.dist-info/RECORD
