Metadata-Version: 2.4
Name: beets-folkways
Version: 0.1.2
Summary: Beets metadata plugin to fetch folkways record data.
Author-email: Sebastian Hugentobler <shu+pypi@vanwa.ch>
License-Expression: GPL-3.0-or-later
Project-URL: source, https://code.vanwa.ch/shu/beets-folkways
Requires-Python: >=3.13
Requires-Dist: beautifulsoup4>=4.14.3
Requires-Dist: beets>=2.5.1
Requires-Dist: requests>=2.32.5
